{
  "total":"3",
  "records":"9",
  "page":"1",
  "rows":[
    {
      "id":"1",
      "title":"标题",
      "src":"音频",
      "duration":"时长",
      "upload_time":"上传时间",
      "size":"大小",
      "album_id":"专辑id"
    },{
      "id":"1",
      "title":"标题",
      "src":"音频",
      "duration":"时长",
      "upload_time":"上传时间",
      "size":"大小",
      "album_id":"专辑id"
    },{
      "id":"1",
      "title":"标题",
      "src":"音频",
      "duration":"时长",
      "upload_time":"上传时间",
      "size":"大小",
      "album_id":"专辑id"
    },{
      "id":"1",
      "title":"标题",
      "src":"音频",
      "duration":"时长",
      "upload_time":"上传时间",
      "size":"大小",
      "album_id":"专辑id"
    },{
      "id":"1",
      "title":"标题",
      "src":"音频",
      "duration":"时长",
      "upload_time":"上传时间",
      "size":"大小",
      "album_id":"专辑id"
    },{
      "id":"1",
      "title":"标题",
      "src":"音频",
      "duration":"时长",
      "upload_time":"上传时间",
      "size":"大小",
      "album_id":"专辑id"
    }
  ]
}